MANIFEST.in
README.md
requirements.txt
setup.py
django_tawea.egg-info/PKG-INFO
django_tawea.egg-info/SOURCES.txt
django_tawea.egg-info/dependency_links.txt
django_tawea.egg-info/top_level.txt
tawea/__init__.py
tawea/templates/tawea/tawea.html
tawea/templatetags/__init__.py
tawea/templatetags/tawea.py