Metadata-Version: 1.1
Name: django-tawea
Version: 0.1
Summary: Add Facebook chat (Tawea) to a template with a simple tag.
Home-page: https://github.com/javimb/django-tawea
Author: Javi Imbernon
Author-email: javi@javimb.com
License: BSD
Platform: UNKNOWN
Classifier: Environment :: Web Environment
Classifier: Framework :: Django
Classifier: Intended Audience :: Developers
Classifier: License :: OSI Approved :: BSD License
Classifier: Operating System :: OS Independent
Classifier: Programming Language :: Python
Classifier: Programming Language :: Python :: 2.6
Classifier: Programming Language :: Python :: 2.7
Classifier: Topic :: Internet :: WWW/HTTP
Classifier: Topic :: Internet :: WWW/HTTP :: Dynamic Content
